pyrmm-0.3.6.dist-info/METADATA
pyrmm-0.3.6.dist-info/WHEEL
pyrmm-0.3.6.dist-info/entry_points.txt
pyrmm-0.3.6.dist-info/licenses/LICENSE
pyrmm/__init__.py
pyrmm/ai/rmmcp.py
pyrmm/cli/__init__.py
pyrmm/cli/nb.py
pyrmm/cli/publish.py
pyrmm/cli/rmmcore.cp313-win_amd64.pyd
pyrmm/cli/rmmcore.pyi
pyrmm/py.typed
pyrmm/utils/proxy.py
pyrmm-0.3.6.dist-info/RECORD
