Metadata-Version: 2.4
Name: pyrmm
Version: 0.3.6
Requires-Dist: click>=8.2.1
Requires-Dist: maturin>=1.9.5
Requires-Dist: mcp[cli]>=1.9.4
Requires-Dist: pygithub>=2.6.1
Requires-Dist: requests>=2.32.4
Requires-Dist: toml>=0.10.2
Requires-Dist: pytest>=8.4.0 ; extra == 'dev'
Requires-Dist: pytest-cov>=6.2.0 ; extra == 'dev'
Requires-Dist: black>=25.1.0 ; extra == 'dev'
Requires-Dist: isort>=6.0.0 ; extra == 'dev'
Requires-Dist: maturin>=1.8.0 ; extra == 'dev'
Provides-Extra: dev
License-File: LICENSE
Summary: Magisk/Apatch/Kernelsu模块的工具集
Home-Page: https://github.com/LIghtJUNction/RootManageModuleModel
Author-email: LIghtJUNction <LIghtJUNction.me@gmail.com>
License: MIT
Requires-Python: >=3.11
